{
  "Header": {
    "WolvenKitVersion": "8.11.0",
    "WKitJsonVersion": "0.0.9",
    "GameVersion": 2200,
    "ExportedDateTime": "2026-05-19T03:47:10.364Z",
    "DataType": "CR2W",
    "ArchiveFileName": ""
  },
  "Data": {
    "Version": 195,
    "BuildVersion": 0,
    "RootChunk": {
      "$type": "Multilayer_Setup",
      "cookingPlatform": "PLATFORM_PC",
      "layers": [
        {
          "$type": "Multilayer_Layer",
          "colorScale": {
            "$type": "CName",
            "$storage": "string",
            "$value": "adc4d0_null"
          },
          "material": {
            "DepotPath": {
              "$type": "ResourcePath",
              "$storage": "string",
              "$value": "base\\surfaces\\materials\\glass\\windows_opaque\\windows_opaque_foil_01_200.mltemplate"
            },
            "Flags": "Default"
          },
          "matTile": 10.10,
          "mbTile": 10.1000004,
          "metalLevelsIn": {
            "$type": "CName",
            "$storage": "string",
            "$value": "null"
          },
          "metalLevelsOut": {
            "$type": "CName",
            "$storage": "string",
            "$value": "null"
          },
          "microblend": {
            "DepotPath": {
              "$type": "ResourcePath",
              "$storage": "string",
              "$value": "base\\surfaces\\microblends\\default.xbm"
            },
            "Flags": "Default"
          },
          "microblendContrast": 0.50,
          "microblendNormalStrength": 0.01,
          "microblendOffsetU": 0,
          "microblendOffsetV": 0,
          "normalStrength":{
            "$type": "CName",
            "$storage": "string",
            "$value": "null"
          },
          "offsetU": 0,
          "offsetV": 0,
          "overrides": {
            "$type": "CName",
            "$storage": "string",
            "$value": "None"
          },
          "roughLevelsIn": {
            "$type": "CName",
            "$storage": "string",
            "$value": "null"
          },
          "roughLevelsOut": {
            "$type": "CName",
            "$storage": "string",
            "$value": "null"
          }
        },
        {
          "$type": "Multilayer_Layer",
          "colorScale": {
            "$type": "CName",
            "$storage": "string",
            "$value": "adc4d0_null"
          },
          "material": {
            "DepotPath": {
              "$type": "ResourcePath",
              "$storage": "string",
              "$value": "base\\surfaces\\materials\\glass\\windows_opaque\\windows_opaque_foil_01_200.mltemplate"
            },
            "Flags": "Default"
          },
          "matTile": 10.10,
          "mbTile": 10.1000004,
          "metalLevelsIn": {
            "$type": "CName",
            "$storage": "string",
            "$value": "null"
          },
          "metalLevelsOut": {
            "$type": "CName",
            "$storage": "string",
            "$value": "null"
          },
          "microblend": {
            "DepotPath": {
              "$type": "ResourcePath",
              "$storage": "string",
              "$value": "base\\surfaces\\microblends\\default.xbm"
            },
            "Flags": "Default"
          },
          "microblendContrast": 0.50,
          "microblendNormalStrength": 0.01,
          "microblendOffsetU": 0,
          "microblendOffsetV": 0,
          "normalStrength":{
            "$type": "CName",
            "$storage": "string",
            "$value": "null"
          },
          "offsetU": 0,
          "offsetV": 0,
          "opacity": 0.0599999987,
          "overrides": {
            "$type": "CName",
            "$storage": "string",
            "$value": "None"
          },
          "roughLevelsIn": {
            "$type": "CName",
            "$storage": "string",
            "$value": "null"
          },
          "roughLevelsOut": {
            "$type": "CName",
            "$storage": "string",
            "$value": "null"
          }
        },
        {
          "$type": "Multilayer_Layer",
          "colorScale": {
            "$type": "CName",
            "$storage": "string",
            "$value": "adc4d0_null"
          },
          "material": {
            "DepotPath": {
              "$type": "ResourcePath",
              "$storage": "string",
              "$value": "base\\surfaces\\materials\\glass\\windows_opaque\\windows_opaque_foil_streaky_01_200.mltemplate"
            },
            "Flags": "Default"
          },
          "matTile": 10.10,
          "mbTile": 10.1000004,
          "metalLevelsIn": {
            "$type": "CName",
            "$storage": "string",
            "$value": "null"
          },
          "metalLevelsOut": {
            "$type": "CName",
            "$storage": "string",
            "$value": "null"
          },
          "microblend": {
            "DepotPath": {
              "$type": "ResourcePath",
              "$storage": "string",
              "$value": "base\\surfaces\\microblends\\default.xbm"
            },
            "Flags": "Default"
          },
          "microblendContrast": 0.50,
          "microblendNormalStrength": 0.01,
          "microblendOffsetU": 0,
          "microblendOffsetV": 0,
          "normalStrength":{
            "$type": "CName",
            "$storage": "string",
            "$value": "null"
          },
          "offsetU": 0,
          "offsetV": 0,
          "overrides": {
            "$type": "CName",
            "$storage": "string",
            "$value": "None"
          },
          "roughLevelsIn": {
            "$type": "CName",
            "$storage": "string",
            "$value": "null"
          },
          "roughLevelsOut": {
            "$type": "CName",
            "$storage": "string",
            "$value": "null"
          }
        },
        {
          "$type": "Multilayer_Layer",
          "colorScale": {
            "$type": "CName",
            "$storage": "string",
            "$value": "adc4d0_null"
          },
          "material": {
            "DepotPath": {
              "$type": "ResourcePath",
              "$storage": "string",
              "$value": "base\\surfaces\\materials\\glass\\windows_opaque\\windows_opaque_foil_01_200.mltemplate"
            },
            "Flags": "Default"
          },
          "matTile": 10.10,
          "mbTile": 10.1000004,
          "metalLevelsIn": {
            "$type": "CName",
            "$storage": "string",
            "$value": "null"
          },
          "metalLevelsOut": {
            "$type": "CName",
            "$storage": "string",
            "$value": "null"
          },
          "microblend": {
            "DepotPath": {
              "$type": "ResourcePath",
              "$storage": "string",
              "$value": "base\\surfaces\\microblends\\default.xbm"
            },
            "Flags": "Default"
          },
          "microblendContrast": 0.50,
          "microblendNormalStrength": 0.01,
          "microblendOffsetU": 0,
          "microblendOffsetV": 0,
          "normalStrength":{
            "$type": "CName",
            "$storage": "string",
            "$value": "null"
          },
          "offsetU": 0,
          "offsetV": 0,
          "overrides": {
            "$type": "CName",
            "$storage": "string",
            "$value": "None"
          },
          "roughLevelsIn": {
            "$type": "CName",
            "$storage": "string",
            "$value": "null"
          },
          "roughLevelsOut": {
            "$type": "CName",
            "$storage": "string",
            "$value": "null"
          }
        },
        {
          "$type": "Multilayer_Layer",
          "colorScale": {
            "$type": "CName",
            "$storage": "string",
            "$value": "adc4d0_null"
          },
          "material": {
            "DepotPath": {
              "$type": "ResourcePath",
              "$storage": "string",
              "$value": "base\\surfaces\\materials\\glass\\windows_opaque\\windows_opaque_foil_01_200.mltemplate"
            },
            "Flags": "Default"
          },
          "matTile": 10.10,
          "mbTile": 10.1000004,
          "metalLevelsIn": {
            "$type": "CName",
            "$storage": "string",
            "$value": "null"
          },
          "metalLevelsOut": {
            "$type": "CName",
            "$storage": "string",
            "$value": "null"
          },
          "microblend": {
            "DepotPath": {
              "$type": "ResourcePath",
              "$storage": "string",
              "$value": "base\\surfaces\\microblends\\default.xbm"
            },
            "Flags": "Default"
          },
          "microblendContrast": 0.50,
          "microblendNormalStrength": 0.01,
          "microblendOffsetU": 0,
          "microblendOffsetV": 0,
          "normalStrength":{
            "$type": "CName",
            "$storage": "string",
            "$value": "null"
          },
          "offsetU": 0,
          "offsetV": 0,
          "overrides": {
            "$type": "CName",
            "$storage": "string",
            "$value": "None"
          },
          "roughLevelsIn": {
            "$type": "CName",
            "$storage": "string",
            "$value": "null"
          },
          "roughLevelsOut": {
            "$type": "CName",
            "$storage": "string",
            "$value": "null"
          }
        }
      ],
      "ratio": 1,
      "useNormal": 1
    },
    "EmbeddedFiles": []
  }
}